idtxl/__init__.py
idtxl/active_information_storage.py
idtxl/bivariate_mi.py
idtxl/bivariate_pid.py
idtxl/bivariate_te.py
idtxl/data.py
idtxl/data_spiketime.py
idtxl/embedding_optimization_ais_Rudelt.py
idtxl/estimator.py
idtxl/estimators_Rudelt.py
idtxl/estimators_jidt.py
idtxl/estimators_mpi.py
idtxl/estimators_multivariate_pid.py
idtxl/estimators_opencl.py
idtxl/estimators_pid.py
idtxl/estimators_python.py
idtxl/gpuKnnKernelNoIdx.cl
idtxl/hde_fast_embedding.pyx
idtxl/hde_fast_embedding_utils.py
idtxl/hde_setup.py
idtxl/hde_utils.py
idtxl/idtxl_exceptions.py
idtxl/idtxl_import.py
idtxl/idtxl_io.py
idtxl/idtxl_utils.py
idtxl/infodynamics.jar
idtxl/lattices.py
idtxl/multivariate_mi.py
idtxl/multivariate_pid.py
idtxl/multivariate_te.py
idtxl/network_analysis.py
idtxl/network_comparison.py
idtxl/network_inference.py
idtxl/pid_goettingen.py
idtxl/postprocessing.py
idtxl/results.py
idtxl/setup_hde_fast_embedding.py
idtxl/single_process_analysis.py
idtxl/stats.py
idtxl/synergy_tartu.py
idtxl/visualise_graph.py
idtxl/knn/__init__.py
idtxl/knn/knn_finder.py
idtxl/knn/knn_finder_factory.py
idtxl/knn/knn_finder_scipy.py
idtxl/knn/knn_finder_sklearn.py
idtxl/knn/tree_knn_finder.py
idtxl_uv-1.6.1.dist-info/METADATA
idtxl_uv-1.6.1.dist-info/WHEEL
idtxl_uv-1.6.1.dist-info/licenses/LICENSE
idtxl_uv-1.6.1.dist-info/RECORD
