Metadata-Version: 2.4
Name: idtxl-uv
Version: 1.6.1
Summary: Information Dynamics Toolkit xl - UV package manager fork
Project-URL: Homepage, https://github.com/pwollstadt/IDTxl
Project-URL: Fork, https://github.com/jansturm1/IDTxl
Author: Joseph T. Lizier, Raul Vicente, Conor Finn, Mario Martinez-Zarzuela, Pedro Mediano, Leonardo Novelli, Michael Wibral
Author-email: Patricia Wollstadt <p.wollstadt@gmail.com>
Maintainer-email: Jan Sturm <jansturm1@gmail.com>
License: GPL-3.0-only
License-File: LICENSE
Classifier: Development Status :: 5 - Production/Stable
Classifier: Environment :: Console
Classifier: Environment :: Other Environment
Classifier: Intended Audience :: Science/Research
Classifier: Operating System :: POSIX :: Linux
Classifier: Programming Language :: Python
Classifier: Programming Language :: Python :: 3
Classifier: Topic :: Scientific/Engineering :: Bio-Informatics
Classifier: Topic :: Scientific/Engineering :: Information Analysis
Classifier: Topic :: Scientific/Engineering :: Medical Science Apps.
Classifier: Topic :: Scientific/Engineering :: Physics
Requires-Python: >=3.7
Requires-Dist: ecos>=2.0.14
Requires-Dist: h5py>=3.8.0
Requires-Dist: jpype1>=1.5.0
Requires-Dist: matplotlib>=3.5.3
Requires-Dist: mpi4py>=4.0.3
Requires-Dist: networkx>=2.6.3
Requires-Dist: prettytable>=3.7.0
Requires-Dist: pyopencl>=2022.2.4
Requires-Dist: siphash24>=1.7
Requires-Dist: statsmodels>=0.13.5
